{
  "item_arrow_greenmetal": "Siyah metal ok",
  "item_arrow_greenmetal_description": "Bir delici karanlık, umarım nişan alır.",
  "item_bone_arrow": "Kemik ok",
  "item_bone_arrow_description": "Sadece bir gri cüceye bir kemik vermek.",
  "item_arrow_surtlingfire": "Surtling ateş oku",
  "item_arrow_surtlingfire_description": "Bu güvenli görünmüyor, umarım nişan aldığınız şey için daha güvenli olur.",
  "item_ancient_arrow": "Antik ahşap ok",
  "item_ancient_arrow_description": "Her an parçalanabilir gibi görünüyor.",
  "item_arrow_chitin": "Kitin ok",
  "item_arrow_chitin_description": "Diğer oklar kadar keskin olmasa da yine de kötü bir kesik oluşturuyor.",
  "item_bolt_wood": "Çekirdek tahtası cıvata",
  "item_bolt_wood_description": "Biraz daha sivri bir çubuktan fazlası. Sert bir şekilde atıldığında hala acıtıyor!",
  "item_bolt_bronze": "Bronz cıvata",
  "item_bolt_bronze_description": "Bronz crossbow, corewooddan biraz daha keskin.",
  "item_bolt_iron_poison": "Demir zehir cıvatası",
  "item_bolt_iron_poison_description": "Zehirle kaplanmış keskin bir demir cıvata, ölümü hızlandırıyor.",
  "item_bolt_silver_frost": "Gümüş buz cıvatası",
  "item_bolt_silver_frost_description": "Buzla kaplanmış gümüş cıvatalar, ateşli ve ölülere karşı ölümcül.",
  "item_bolt_surtling": "Blackmetal surtling cıvatası",
  "item_bolt_surtling_description": "Bir surtling çekirdeği barındıran bir blackmetal çekirdek, bu yanacak.",
  "item_bolt_obsidian": "Obsidyen cıvatası",
  "item_bolt_obsidian_description": "Tamamen karanlık bir parça.",
  "item_arbalist_bronze": "Bronz arbelist",
  "item_arbalist_bronze_description": "Arbelist, crossbowun gücünde büyük bir iyileşme, ancak biraz daha kullanışsız.",
  "item_crossbow_bronze": "Bronz crossbow",
  "item_crossbow_bronze_description": "Basit bir bronz crossbow, güçlü ama kırılgan.",
  "item_sword_chitin": "Abyssal kılıç",
  "item_sword_chitin_description": "Belki en keskin değil ama yeterince güçle hala çok acıtıyor.",
  "item_sword_flint": "Çakmaktaşı kılıcı",
  "item_sword_flint_description": "Bulabileceğiniz en iyi çakmaktaşından yapılmış, hala biraz çelimsiz.",
  "item_serpent_buckler": "Yılan ölçekli kalkan",
  "item_serpent_buckler_description": "Esnek bir demir örgü kalkan, parlak pulların önünde.",
  "item_atgeir_flint": "Çakmaktaşı atgeir",
  "item_atgeir_flint_description": "Büyük bir çakmaktaşı parçasıyla beceriksizce bağlanmış basit bir direk.",
  "item_atgeir_chitin_heavy": "Kraliyet abyssal atgeir",
  "item_atgeir_chitin_heavy_description": "Gümüş çekirdekli bir keskin kitin atgeir, en cesur vikingler için uygun.",
  "item_silver_atgeir": "Gümüş atgeir",
  "item_silver_atgeir_description": "Obsidyenle desteklenmiş dev bir gümüş bıçak, bir avcı silahı.",
  "item_sledge_blackmetal": "Gökyüzü çekiç",
  "item_sledge_blackmetal_description": "Göktaşı ile birleştirilmiş ağır parçalar. Yıldırım çarpmalarına neden oluyor. Kıymetini hak eden bir savaş çekici.",
  "item_battleaxe_flint": "Çakmaktaşı savaş baltası",
  "item_battleaxe_flint_description": "Sağlam bir kütüğe iki rastgele bağlanmış çakmaktaşı bıçak.",
  "item_battleaxe_bronze": "Tomruk savaş baltası",
  "item_battleaxe_bronze_description": "Başları ve ağaçları çıkarmak için harika bir büyük bronz balta.",
  "item_battleaxe_blackmetal": "Herkir'ın gazabı",
  "item_battleaxe_blackmetal_description": "Dev katil, ateş getirici, acı verici.",
  "item_flint_greatsword": "Çakmaktaşı büyük kılıç",
  "item_flint_greatsword_description": "Tahtadan desteklenmiş dev çakmaktaşı parçası. Çok dayanıklı olmasa da yeterince keskin.",
  "item_bronze_greatsword": "Bronz büyük kılıç",
  "item_bronze_greatsword_description": "Çekirdek tahtası ile taşınan dev bir bronz bıçak, çok dayanıklı değil ama oldukça keskin.",
  "item_iron_greatsword": "Demir büyük kılıç",
  "item_iron_greatsword_description": "Kaba bir demir bıçak büyük bir taş sapla. Yeterince büyük bir bıçakla, her şey ölür.",
  "item_silver_greatsword": "Gümüş runik büyük kılıç",
  "item_silver_greatsword_description": "Ölüleri uzak tutmak için runik işaretlerle süslenmiş demirle dövülmüş gümüş.",
  "item_dagger_flint_2h": "Çakmaktaşı hançerler",
  "item_dagger_flint_2h_description": "İki çakmaktaşı bıçak bir taneden daha ölümcül.",
  "item_dagger_iron": "Demir hançer",
  "item_dagger_iron_description": "Abyssal bıçak kadar keskin değil ama güzelce kesiyor.",
  "item_dagger_iron_2h": "Rogue hançerler",
  "item_dagger_iron_2h_description": "İki demir bıçak seni ortalama bir viking casusu yapar.",
  "item_dagger_bronze": "Bronz hançer",
  "item_dagger_bronze_description": "Bakırdan daha keskin, delici bir saplama.",
  "item_dagger_bronze_2h": "Hain hançerler",
  "item_dagger_bronze_description_2h": "Şimdi sadece cepçilik becerinizi geliştirmeniz gerekiyor.",
  "item_dagger_silver": "Gümüş hançer",
  "item_dagger_silver_description": "Runelerle süslenmiş keskin bir gümüş kısa bıçak.",
  "item_dagger_silver_2h": "Blackguard runik hançerler",
  "item_dagger_silver_2h_description": "İnsanlar ve yaratıklar dilimlenmekten korkar.",
  "item_fist_flint": "Çakmaktaşı yularlar",
  "item_fist_flint_description": "Çakmaktaşı parçaları üzerine sabitlenmiş birkaç tahtadan oluşan sivri bir çubuk, ellerinizden daha fazla acıtıyor.",
  "item_fist_bronze": "Bronz yularlar",
  "item_fist_bronze_description": "Çekirdek tahtası destekli bronz dikenler, şimdi bu güçlü bir darbe yapar.",
  "item_fist_iron": "Demir yularlar",
  "item_fist_iron_description": "Sağlam bıçaklarla uçları keskin, bu yumruk bıçakları her darbe vurduğunda dilimlenme yapıyor.",
  "va_staff_eitr_buff": "Antik büyüler",
  "va_staff_eitr_buff_desc": "Bu büyülü değnek sana bir miktar Eitr'ye erişim sağlıyor.",
  "item_staff_poison": "Zehirli değnek",
  "item_staff_poison_description": "Çok eski ağaçlardan yapılmış güçlü bir değnek, yıllardır içine çektiği zehir kokuyor.",
  "item_staff_druid_poison": "Zehirli druidik değnek",
  "item_staff_druid_poison_description": "Bataklıktan gelen sihirli özlerle yapılmış bir Druidlerin değneği, büyük bir odakla bununla zehir yaratabilirsin.",
  "item_staff_spirit": "Ruh değneği",
  "item_staff_spirit_description": "Yaşlıların ruhu ve güçlü sihirli unsurlarla yapılmış bir değnek. Ölüler ondan korkuyor.",
  "item_staff_druid_spirit": "Ruh druidik değnek",
  "item_staff_druid_spirit_description": "Kara ormandan gelen sihirli eşyalarla yapılmış bir Druidlerin değneği, ölüler ondan çekiniyor.",
  "item_staff_druid_ice": "Buz druidik değnek",
  "item_staff_druid_ice_description": "Dağ buz kristallerinden yapılmış dondurucu bir Druidlerin değneği.",
  "item_staff_druid_fire": "Ateş druidik değnek",
  "item_staff_druid_fire_description": "Dikkatlice kontrol edilen bir ateş, bir Druidlerin değneğine monte edilmiş, bakalım goblin şamanları bunu nasıl bulacak.",
  "item_bow_antler": "Boynuz yayı",
  "item_bow_antler_description": "Yıldırımın habercisi, herkes Eikthyr'ın gök gürültüsünü duysun.",
  "item_dagger_antler": "Boynuz hançeri",
  "item_dagger_antler_description": "Eikthyr'ın boynuzlarından bir parça keskinleştirilmiş, hala elektrikle dolu.",
  "item_sword_antler": "Boynuz kılıcı",
  "item_sword_antler_description": "Eikthyrs'ın kalıntılarından zincirlerle bağlanmış kıvrılmış boynuzlar, hala enerji dolu.",
  "item_atgeir_antler": "Boynuz atgeir",
  "item_atgeir_antler_description": "Eikthyr'ın tacından bir dal hala kıvılcımlar saçarak bir direğe bağlanmış, Antlergeir.",
  "item_battleaxe_antler": "Boynuz savaş baltası",
  "item_battleaxe_antler_description": "İki boynuz keskinleştirilip zincirlenmiş, hala Eikthyr'ın hayatıyla kıvılcım saçıyorlar.",
  "va_vineshield_resistance": "Sağlam hissediyorsun.",
  "va_vineshield_resistance_description": "Elders vineshield, ruh ve zehire karşı güçlü dirençler sağlıyor.",
  "item_sledge_elder": "Sarmaşık çekiç",
  "item_sledge_elder_description": "Elder'ın kendisinin kanıyla birleşmiş canlı sarmaşıklarla birleştirilmiş dev bir taş.",
  "item_elder_roundshield": "Sarmaşık kalkanı",
  "item_elder_roundshield_description": "Elder'ın kanıyla birleşmiş sarmaşıklar.",
  "item_crossbow_elder": "Sarmaşık crossbow",
  "item_crossbow_elder_description": "Canlı sarmaşıklarla gerilmiş bir crossbow, umarım daha fazla büyümezler.",
  "item_elder_mace": "Sarmaşık mızrağı",
  "item_elder_mace_description": "Canlı sarmaşıklarla birleştirilmiş büyük bir taş, hala sürgünlerini çağırıyor.",
  "item_sword_vine": "Sarmaşık kılıcı",
  "item_sword_vine_description": "Dikkatlice dengelenmiş bir taş bıçak, Elder'ın sarmaşıklarıyla birleşmiş.",
  "item_bonemass_warhammer": "Kafatası çekiç",
  "item_bonemass_warhammer_description": "Ölülerin kafataslarından yapılmış güçlü bir savaş çekiç, bonemass'ın nefretiyle doldurulmuş.",
  "item_bonemass_greatsword": "Kemik kılıç",
  "item_bonemass_greatsword_description": "Bir kafatasına monte edilmiş dev bir eski kemik keskinleştirilmiş uca.",
  "item_bonemass_dagger": "Zehirli kemik hançeri",
  "item_bonemass_dagger_description": "Zehirle kaplanmış ince bir demir bıçak, ölülerin kemikleriyle süslenmiş.",
  "va_modershield_resistance": "Elementler daha dayanılabilir görünüyor.",
  "va_modershield_resistance_description": "Moder'ün kalkanı sana büyük bir donma direnci ve küçük bir ateş direnci sağlıyor.'",
  "item_spear_moder": "Ejderha buz mızrağı",
  "item_spear_moder_description": "Ejderha gözyaşlarından sürekli donmuş bir buz mızrağı.",
  "item_sword_moder": "Ejderha buz kılıcı",
  "item_sword_moder_description": "Ejderha gözyaşlarının özüyle sürekli soğutulmuş bir buzdan uzun kılıç.",
  "item_crossbow_moder": "Ejderha buz crossbow",
  "item_crossbow_moder_description": "Moder'ün gözyaşlarının bir çekirdek tarafından güçlendirilmiş çift bileşik yayla çalışan bir crossbow.",
  "item_moder_buckler": "Ejderha buz kalkanı",
  "item_moder_buckler_description": "Ejderha kanıyla işlenmiş bu kalkan, her zaman ılık bir sıcaklık yayar, kullanıcısını donmaya karşı yüksek dirençli hale getirir.",
  "item_yagluth_atgeir": "Goblin kral atgeiri",
  "item_yagluth_atgeir_description": "Yagluth'un tacından bir parça, bir mızrağa monte edilmiş, hala ölmeyen bir ateş öfkesi yayar.",
  "item_yagluth_greatsword": "Goblin kral büyük kılıcı",
  "item_yagluth_greatsword_description": "Blackmetal ve Yagluth'un kalıntılarından yapılmış dev bir kılıç.",
  "item_fist_yagluth": "Goblin kralın yularları",
  "item_fist_yagluth_description": "Demir ve blackmetal tarafından korunan goblin-kralın tacından parçalar.",
  "va_queen_buff": "Kraliçenin varlığı",
  "va_queen_buff_desc": "Kraliçenin gücü seninle akıyor, kendini enerjik ve sağlıklı hissediyorsun.",
  "item_bow_pincer": "Kıskaç büyük yayı",
  "item_bow_pincer_description": "Kraliçenin iki kıskaçtan yapılmış dev yayı, gerilmesi büyük bir enerji gerektiriyor ama oldukça etkili.",
  "item_sword_queen": "Kapak kılıcı",
  "item_sword_queen_description": "Kraliçe böceğin keskin kabuğundan yapılmış, hala sihirli enerji yayar.",
  "item_queen_greatsword": "Kıskaç büyük kılıç",
  "item_queen_greatsword_description": "Mühürlü kraliçenin dev bir kıskaçı, hala zaman zaman biraz titriyor gibi görün",
  "item_dagger_queen": "Kara kabuk bıçağı",
  "item_dagger_queen_description": "Kraliçenin devasa kabuğundan bir parça, onun sihriyle parlıyor.",
  "item_bow_bone_blood": "Kan kemik yay.",
  "item_bow_bone_blood_description": "Çekirdek odunu ve kemiklerden yapılan yayın kötü bir havası var, oklara ihtiyaç duymuyor, ancak okçunun kanını emiyor.",
  "item_pickaxe_blood": "Kan kemik savaş baltası",
  "item_pickaxe_blood_description": "Bu kazma doğal olmayan bir şekilde güçlü görünüyor ve kanınızı istiyor.",
  "va_blood_sucker": "Kan Çılgınlığı",
  "va_blood_sucker_desc": "Silahın kan için istekli."
}